multiviewae/__init__.py
multiviewae/architectures/__init__.py
multiviewae/architectures/cnn.py
multiviewae/architectures/mlp.py
multiviewae/base/__init__.py
multiviewae/base/base_model.py
multiviewae/base/constants.py
multiviewae/base/dataloaders.py
multiviewae/base/datasets.py
multiviewae/base/distributions.py
multiviewae/base/exceptions.py
multiviewae/base/representations.py
multiviewae/base/validation.py
multiviewae/configs/__init__.py
multiviewae/configs/default.yaml
multiviewae/configs/model_type/AE.yaml
multiviewae/configs/model_type/DCCAE.yaml
multiviewae/configs/model_type/DMVAE.yaml
multiviewae/configs/model_type/DVCCA.yaml
multiviewae/configs/model_type/JMVAE.yaml
multiviewae/configs/model_type/MoPoEVAE.yaml
multiviewae/configs/model_type/mAAE.yaml
multiviewae/configs/model_type/mVAE.yaml
multiviewae/configs/model_type/mWAE.yaml
multiviewae/configs/model_type/mcVAE.yaml
multiviewae/configs/model_type/me_mVAE.yaml
multiviewae/configs/model_type/mmJSD.yaml
multiviewae/configs/model_type/mmVAE.yaml
multiviewae/configs/model_type/mmVAEPlus.yaml
multiviewae/configs/model_type/mvtCAE.yaml
multiviewae/configs/model_type/weighted_DMVAE.yaml
multiviewae/configs/model_type/weighted_mVAE.yaml
multiviewae/models/DMVAE.py
multiviewae/models/__init__.py
multiviewae/models/ae.py
multiviewae/models/dccae.py
multiviewae/models/dvcca.py
multiviewae/models/jmvae.py
multiviewae/models/maae.py
multiviewae/models/mcvae.py
multiviewae/models/me_mvae.py
multiviewae/models/mmJSD.py
multiviewae/models/mmvae.py
multiviewae/models/mmvaeplus.py
multiviewae/models/mopoevae.py
multiviewae/models/mvae.py
multiviewae/models/mvtcae.py
multiviewae/models/mwae.py
multiviewae/models/weighted_DMVAE.py
multiviewae/models/weighted_mvae.py
multiviewae-1.1.8.dist-info/LICENSE.md
multiviewae-1.1.8.dist-info/METADATA
multiviewae-1.1.8.dist-info/WHEEL
multiviewae-1.1.8.dist-info/RECORD
