Metadata-Version: 2.1
Name: multiviewae
Version: 1.1.8
Summary: A library for running multiview autoencoder models
License: MIT
Author: analawryaguila
Author-email: ana.lawryaguila@outlook.com
Requires-Python: >=3.6,<4.0
Classifier: License :: OSI Approved :: MIT License
Classifier: Programming Language :: Python :: 3
Classifier: Programming Language :: Python :: 3.6
Classifier: Programming Language :: Python :: 3.7
Classifier: Programming Language :: Python :: 3.8
Classifier: Programming Language :: Python :: 3.9
Classifier: Programming Language :: Python :: 3.10
Classifier: Programming Language :: Python :: 3.11
Classifier: Programming Language :: Python :: 3.12
Requires-Dist: hydra-core
Requires-Dist: matplotlib
Requires-Dist: numpy
Requires-Dist: ordereddict
Requires-Dist: pandas
Requires-Dist: pytest (>=5.4.1,<6.0.0)
Requires-Dist: pytest-cov
Requires-Dist: pytorch-lightning (==1.5.10)
Requires-Dist: schema
Requires-Dist: scipy
Requires-Dist: tensorboard
Requires-Dist: torch
Requires-Dist: torchvision
Project-URL: Documentation, https://multi-view-ae.readthedocs.io/en/latest/
